{
    "version": "https://jsonfeed.org/version/1",
    "title": "⭐️齐下无贰⭐️ • All posts by \"成长路线\" tag",
    "description": "May all the beauty be bless.✨",
    "home_page_url": "https://weidows.github.io",
    "items": [
        {
            "id": "https://weidows.github.io/post/others/LearnWay/",
            "url": "https://weidows.github.io/post/others/LearnWay/",
            "title": "😍Weidows の成长路线.",
            "date_published": "2020-12-30T03:42:22.000Z",
            "content_html": "<!--\n * @?: *********************************************************************\n * @Author: Weidows\n * @Date: 2020-12-30 11:42:22\n * @LastEditors: Weidows\n * @LastEditTime: 2022-02-17 02:41:33\n * @FilePath: \\Blog-private\\source\\_posts\\others\\LearnWay.md\n * @Description:\n * @!: *********************************************************************\n-->\n<h1>😍Weidows の成长路线.</h1>\n<blockquote class=\"pullquote mindmap mindmap-md\"><ul>\n<li><a href=\"#weidows-%E3%81%AE%E6%88%90%E9%95%BF%E8%B7%AF%E7%BA%BF\">😍Weidows の成长路线.</a>\n<ul>\n<li><a href=\"#java\">Java</a>\n<ul>\n<li><a href=\"#%E9%98%B6%E6%AE%B5\">阶段</a>\n<ul>\n<li><a href=\"#%E5%85%A5%E9%97%A8\">入门</a></li>\n<li><a href=\"#%E8%BF%9B%E9%98%B6\">进阶</a></li>\n<li><a href=\"#%E5%B0%B1%E4%B8%9A%E7%BA%A7\">就业级</a></li>\n<li><a href=\"#%E9%98%B6%E6%AE%B5%E5%9B%9E%E9%A1%BE\">阶段回顾</a></li>\n<li><a href=\"#%E7%BD%91%E7%BB%9C%E7%BC%96%E7%A8%8B\">网络编程</a></li>\n<li><a href=\"#javaweb\">JavaWeb</a></li>\n</ul>\n</li>\n<li><a href=\"#%E7%89%B9%E6%80%A7\">特性</a>\n<ul>\n<li><a href=\"#%E6%96%87%E6%A1%A3%E6%B3%A8%E9%87%8A\">文档注释</a></li>\n<li><a href=\"#lambda\">Lambda</a></li>\n<li><a href=\"#%E5%A4%9A%E7%BA%BF%E7%A8%8B\">多线程</a></li>\n<li><a href=\"#%E6%B7%B1%E6%B5%85-clone\">深 / 浅 clone</a></li>\n<li><a href=\"#gui\">GUI</a></li>\n</ul>\n</li>\n<li><a href=\"#%E6%A1%86%E6%9E%B6\">框架</a>\n<ul>\n<li><a href=\"#mybatis\">MyBatis</a></li>\n<li><a href=\"#spring\">Spring</a></li>\n<li><a href=\"#spring-mvc\">Spring MVC</a></li>\n<li><a href=\"#spring-boot\">Spring Boot</a></li>\n<li><a href=\"#%E6%97%A5%E5%BF%97\">日志</a></li>\n</ul>\n</li>\n<li><a href=\"#%E5%B7%A5%E5%85%B7%E7%B1%BB\">工具类</a>\n<ul>\n<li><a href=\"#io\">I/O</a></li>\n<li><a href=\"#optional\">OPTIONAL</a></li>\n<li><a href=\"#url\">URL</a></li>\n<li><a href=\"#stream\">Stream</a></li>\n<li><a href=\"#%E5%8D%95%E5%85%83%E6%B5%8B%E8%AF%95-junit\">单元测试 Junit</a></li>\n</ul>\n</li>\n</ul>\n</li>\n<li><a href=\"#%E5%89%8D%E7%AB%AF\">前端</a>\n<ul>\n<li><a href=\"#htmlcss\">HTML/CSS</a>\n<ul>\n<li><a href=\"#%E5%85%A5%E9%97%A8-1\">入门</a></li>\n<li><a href=\"#%E8%BF%9B%E9%98%B6-1\">进阶</a></li>\n<li><a href=\"#markdown\">Markdown</a></li>\n</ul>\n</li>\n<li><a href=\"#javascript\">JavaScript</a>\n<ul>\n<li><a href=\"#%E8%BF%9B%E9%98%B6-2\">进阶</a></li>\n<li><a href=\"#%E5%BC%82%E6%AD%A5\">异步</a></li>\n<li><a href=\"#console\">Console</a></li>\n<li><a href=\"#%E9%97%AD%E5%8C%85\">闭包</a></li>\n<li><a href=\"#ajax\">Ajax</a></li>\n</ul>\n</li>\n<li><a href=\"#%E5%A4%A7%E5%89%8D%E7%AB%AF\">大前端</a>\n<ul>\n<li><a href=\"#vuejs\">Vue.js</a></li>\n<li><a href=\"#%E8%B7%A8%E5%9F%9F\">跨域</a></li>\n<li><a href=\"#%E5%B7%A5%E5%85%B7%E7%B1%BB-1\">工具类</a></li>\n<li><a href=\"#%E5%85%B6%E4%BB%96\">其他</a></li>\n</ul>\n</li>\n</ul>\n</li>\n<li><a href=\"#%E8%BE%85%E5%8A%A9%E8%AF%AD%E8%A8%80\">辅助语言</a>\n<ul>\n<li><a href=\"#cc\">C/C++</a>\n<ul>\n<li><a href=\"#%E5%85%A5%E9%97%A8%E8%AF%BE%E7%A8%8B\">入门课程</a></li>\n<li><a href=\"#%E8%BF%9B%E9%98%B6%E8%AF%BE%E7%A8%8B\">进阶课程</a></li>\n<li><a href=\"#%E9%93%BE%E8%A1%A8\">链表</a></li>\n</ul>\n</li>\n<li><a href=\"#python\">Python</a>\n<ul>\n<li><a href=\"#%E5%B7%A5%E5%85%B7\">工具</a></li>\n</ul>\n</li>\n</ul>\n</li>\n<li><a href=\"#%E5%BC%80%E5%8F%91%E5%B7%A5%E5%85%B7\">开发工具</a>\n<ul>\n<li><a href=\"#git\">Git</a>\n<ul>\n<li><a href=\"#git-push\">Git push</a></li>\n<li><a href=\"#%E5%A4%9A%E8%BF%9C%E7%A8%8B\">多远程</a></li>\n</ul>\n</li>\n<li><a href=\"#vscode\">VScode</a>\n<ul>\n<li><a href=\"#%E4%B8%BB%E9%A2%98%E9%80%82%E9%85%8D\">主题适配</a></li>\n<li><a href=\"#%E6%8F%92%E4%BB%B6%E5%8C%85%E5%BC%80%E5%8F%91%E5%8F%91%E5%B8%83\">插件 (包) 开发 / 发布</a></li>\n<li><a href=\"#emmet\">Emmet</a></li>\n</ul>\n</li>\n<li><a href=\"#docker\">Docker</a></li>\n<li><a href=\"#%E6%AD%A3%E5%88%99%E8%A1%A8%E8%BE%BE%E5%BC%8F\">正则表达式</a></li>\n</ul>\n</li>\n<li><a href=\"#%E6%B3%9B%E5%9F%9F\">泛域</a>\n<ul>\n<li><a href=\"#2038-%E9%97%AE%E9%A2%98\">2038 问题</a></li>\n<li><a href=\"#%E8%87%AA%E4%BF%A1\">自信</a></li>\n<li><a href=\"#%E7%BC%96%E7%A0%81%E4%B9%A0%E6%83%AF\">编码习惯</a></li>\n<li><a href=\"#%E6%96%87%E6%A1%A3%E7%BC%96%E5%86%99\">文档编写</a></li>\n<li><a href=\"#%E4%BB%A3%E7%90%86\">代理</a></li>\n<li><a href=\"#%E5%9B%BE%E7%81%B5%E6%B5%8B%E8%AF%95\">图灵测试</a></li>\n<li><a href=\"#iaaspaassaas\">IaaS，PaaS，SaaS</a></li>\n</ul>\n</li>\n<li><a href=\"#%E8%AE%BE%E8%AE%A1\">设计</a></li>\n<li><a href=\"#%E7%90%86%E8%AE%BA%E8%AF%BE%E7%A8%8B\">理论课程</a>\n<ul>\n<li><a href=\"#%E6%95%B0%E6%8D%AE%E7%BB%93%E6%9E%84\">数据结构</a></li>\n<li><a href=\"#%E6%93%8D%E4%BD%9C%E7%B3%BB%E7%BB%9F\">操作系统</a>\n<ul>\n<li><a href=\"#%E8%BF%9B%E7%A8%8B%E7%BA%BF%E7%A8%8Bcpu-%E6%A0%B8%E5%BF%83%E5%B9%B6%E8%A1%8C%E5%B9%B6%E5%8F%91\">进程, 线程,CPU 核心, 并行, 并发</a></li>\n</ul>\n</li>\n<li><a href=\"#%E7%BC%96%E8%AF%91%E5%8E%9F%E7%90%86\">编译原理</a></li>\n<li><a href=\"#%E7%A1%AC%E4%BB%B6\">硬件</a></li>\n<li><a href=\"#%E6%95%B0%E6%8D%AE%E5%BA%93\">数据库</a>\n<ul>\n<li><a href=\"#mysql\">MySQL</a></li>\n<li><a href=\"#mongodb\">MongoDB</a></li>\n<li><a href=\"#%E9%80%9A%E7%94%A8\">通用</a></li>\n</ul>\n</li>\n<li><a href=\"#%E8%AE%A1%E7%AE%97%E6%9C%BA%E7%BD%91%E7%BB%9C\">计算机网络</a></li>\n<li><a href=\"#%E7%AE%97%E6%B3%95-%E6%95%B0%E5%AD%A6\">算法 - 数学</a>\n<ul>\n<li><a href=\"#%E5%82%85%E9%87%8C%E5%8F%B6%E5%8F%98%E6%8D%A2\">傅里叶变换</a></li>\n<li><a href=\"#pnp-%E9%97%AE%E9%A2%98\">P/NP 问题</a></li>\n<li><a href=\"#hash-%E7%AE%97%E6%B3%95\">Hash- 算法</a></li>\n<li><a href=\"#%E6%8E%92%E5%BA%8F%E7%AE%97%E6%B3%95\">排序算法</a></li>\n<li><a href=\"#%E5%85%B6%E4%BB%96%E9%9B%B6%E6%95%A3%E7%9A%84\">其他零散的</a></li>\n</ul>\n</li>\n<li><a href=\"#%E8%AE%BA%E6%96%87\">论文</a></li>\n</ul>\n</li>\n<li><a href=\"#%E9%9D%A2%E8%AF%95\">面试</a></li>\n</ul>\n</li>\n</ul>\n</blockquote>\n<p>此篇就 <code>难以及时跟进 </code> 与 <code> 导向不明确</code> 的问题, 考虑当下 [deprecated]; 不久会重构推新!!</p>\n<div class=\"tabs\" id=\"\"><ul class=\"nav-tabs\"><li class=\"tab active\"><button type=\"button\"data-href=\"#-1\">1</button></li><li class=\"tab\"><button type=\"button\"data-href=\"#-2\"><i class=\"fab fa-apple-pay\"></i>为什么写这篇文章 </button></li><li class=\"tab\"><button type=\"button\"data-href=\"#-3\"><i class=\"fas fa-bomb\"></i> 注意</button></li></ul><div class=\"tab-contents\"><div class=\"tab-item-content active\"id=\"-1\"><ul>\n<li>\n<p>有些指引确实有参考价值, 需要结合自身能力和需求体系学习.</p>\n</li>\n<li>\n<p>这个只是个人路线, 并非普遍最优解 (况且很多技术 <code> 已经过时 </code> 了)</p>\n</li>\n</ul><button type=\"button\" class=\"tab-to-top\" aria-label=\"scroll to top\"><i class=\"fas fa-arrow-up\"></i></button></div><div class=\"tab-item-content\" id=\"-2\"><ul>\n<li>\n<p>学习平台比较多, 涉猎范围在 <code> 单方面无法收藏齐全</code>, 这个文章算是概览, 方便寻找.</p>\n<ul>\n<li>比如我在中国大学 MOOC 起步, 在 B 站刷视频课程, 在 CSDN 水技术资料, 在 github 爬高星项目, 在逼乎看技术走向方面的回答.</li>\n</ul>\n</li>\n<li>\n<p><code>此文章只做推荐, 不牵扯任何利益关系.</code></p>\n</li>\n</ul><button type=\"button\" class=\"tab-to-top\" aria-label=\"scroll to top\"><i class=\"fas fa-arrow-up\"></i></button></div><div class=\"tab-item-content\" id=\"-3\"><ul>\n<li>\n<p><code>学习编程是非线性成长</code>, 也就是说在能看懂的情况下都可以学</p>\n<ul>\n<li>\n<p>想速成的话往往效率和方式比较低下, 注意规避.</p>\n</li>\n<li>\n<p>一个技术很大可能会牵扯其他多个技术栈, 能力提升一般呈辐射性网状的.</p>\n</li>\n</ul>\n</li>\n</ul><button type=\"button\" class=\"tab-to-top\" aria-label=\"scroll to top\"><i class=\"fas fa-arrow-up\"></i></button></div></div></div>\n<p><a><img src= \"https://cdn.jsdelivr.net/gh/Weidows/Images/img/loading.webp\" data-lazy-src=\"https://cdn.jsdelivr.net/gh/Weidows/Images/img/divider.png\" alt=\"分割线\"></a></p>\n<h2 id=\"Java\">Java</h2>\n<ul>\n<li>靠翁凯老师入的门, 之后又深挖了其他课程.</li>\n<li>在这里推荐下老师们吧, 不是广告, 只是很感激 <code> 领路人</code>.\n<ul>\n<li><a href=\"https://www.icourse163.org/u/wengkai?userId=318013\">翁凯</a></li>\n<li><a href=\"https://space.bilibili.com/95256449\">狂神 - 秦疆</a></li>\n</ul>\n</li>\n</ul>\n<hr>\n<h3 id=\"阶段\">阶段</h3>\n<h4 id=\"入门\">入门</h4>\n<blockquote>\n<p><a href=\"https://www.icourse163.org/course/0809ZJU013-1001541001?outvandor=zw_mooc_pclszykctj_\">零基础学 Java 语言</a></p>\n</blockquote>\n<hr>\n<h4 id=\"进阶\">进阶</h4>\n<blockquote>\n<p><a href=\"https://www.icourse163.org/course/0809ZJU012-1001542001?outvandor=zw_mooc_pclszykctj_\">面向对象程序设计——Java 语言</a></p>\n</blockquote>\n<hr>\n<h4 id=\"就业级\">就业级</h4>\n<blockquote>\n<p><a href=\"https://www.bilibili.com/video/BV1CJ411m7gg\">求知讲堂零基础 Java 入门编程视频教程 学完可就业</a></p>\n</blockquote>\n<ul>\n<li>个人记录,<code>不推荐 </code> 再学习! 已过时, 而且讲师…不太专业</li>\n</ul>\n<hr>\n<h4 id=\"阶段回顾\">阶段回顾</h4>\n<blockquote>\n<p><a href=\"https://www.bilibili.com/video/BV1MJ411v7tJ?from=search&amp;seid=6413568957300849811\">【狂神说 Java】JavaSE 阶段回顾总结</a></p>\n</blockquote>\n<ul>\n<li>很不错的复习!</li>\n</ul>\n<hr>\n<h4 id=\"网络编程\">网络编程</h4>\n<blockquote>\n<p><a href=\"https://www.bilibili.com/video/BV1LJ411z7vY\">【狂神说 Java】网络编程实战讲解</a> <br>\n<a href=\"https://blog.csdn.net/weixin_45717355/article/details/110945343\">【狂神说 Java】网络编程</a></p>\n</blockquote>\n<hr>\n<h4 id=\"JavaWeb\">JavaWeb</h4>\n<blockquote>\n<p><a href=\"https://www.bilibili.com/video/BV12J411M7Sj\">【狂神说 Java】JavaWeb 入门到实战</a> <br>\n<a href=\"https://blog.csdn.net/bell_love/article/details/105667638\">B 站—【狂神说 Java】JavaWeb 入门到实战—笔记</a></p>\n</blockquote>\n<hr>\n<h3 id=\"特性\">特性</h3>\n<h4 id=\"文档注释\">文档注释</h4>\n<blockquote>\n<p><a href=\"https://blog.csdn.net/lsy0903/article/details/89893934\">Java 文档注释用法 +JavaDoc 的使用详解</a></p>\n</blockquote>\n<hr>\n<h4 id=\"Lambda-2\">Lambda</h4>\n<blockquote>\n<p><a href=\"https://www.runoob.com/java/java8-lambda-expressions.html\">Java Lambda 表达式</a> <br>\n<a href=\"https://objcoding.com/2019/03/04/lambda/\">关于 Java Lambda 表达式看这一篇就够了</a></p>\n</blockquote>\n<hr>\n<h4 id=\"多线程 -2\">多线程</h4>\n<blockquote>\n<p><a href=\"https://www.bilibili.com/video/BV1V4411p7EF\">【狂神说 Java】多线程详解</a> <br>\n<a href=\"https://blog.csdn.net/weixin_41963554/article/details/108808824\">狂神说多线程笔记</a></p>\n</blockquote>\n<hr>\n<h4 id=\"深 - 浅 -clone\">深 / 浅 clone</h4>\n<blockquote>\n<p><a href=\"https://blog.csdn.net/zhangjg_blog/article/details/18369201\">详解 Java 中的 clone 方法 – 原型模式</a></p>\n</blockquote>\n<blockquote>\n<p><a href=\"https://zhidao.baidu.com/question/123775480.html\">java 中深克隆与浅克隆的区别</a></p>\n</blockquote>\n<hr>\n<h4 id=\"GUI\">GUI</h4>\n<blockquote>\n<p><a href=\"https://blog.csdn.net/qq_42035966/article/details/82258199\">Java-GUI 快速入门</a></p>\n</blockquote>\n<hr>\n<h3 id=\"框架\">框架</h3>\n<h4 id=\"MyBatis\">MyBatis</h4>\n<blockquote>\n<p><a href=\"https://www.bilibili.com/video/BV1NE411Q7Nx\">【狂神说 Java】Mybatis 最新完整教程 IDEA 版通俗易懂</a> <br>\n<a href=\"https://blog.csdn.net/DDDDeng_/article/details/106927021\">狂神说 Java Mybatis 笔记</a></p>\n</blockquote>\n<hr>\n<h4 id=\"Spring\">Spring</h4>\n<blockquote>\n<p><a href=\"https://blog.csdn.net/qq_42453117/article/details/104758942\">什么？搞 Java 的你还不会 Spring？一篇文章带你掌握</a> <br>\n<a href=\"https://www.bilibili.com/video/BV1WE411d7Dv\">【狂神说 Java】Spring5 最新完整教程 IDEA 版通俗易懂</a></p>\n</blockquote>\n<hr>\n<h4 id=\"Spring-MVC\">Spring MVC</h4>\n<blockquote>\n<p><a href=\"https://blog.csdn.net/weixin_44635198/article/details/107444925\">SpringMVC 笔记（狂神）</a> <br>\n<a href=\"https://www.bilibili.com/video/BV1aE41167Tu\">【狂神说 Java】SpringMVC 最新教程 IDEA 版通俗易懂</a> <br>\n<a href=\"https://www.cnblogs.com/clwydjgs/p/9255046.html\">@Controller 和 @RestController 的区别？</a> <br>\n<a href=\"https://www.bilibili.com/video/BV1RE41127rv\">【狂神说 Java】SSM 框架最新整合教学 IDEA 版</a></p>\n</blockquote>\n<hr>\n<h4 id=\"Spring-Boot\">Spring Boot</h4>\n<blockquote>\n<p><a href=\"https://blog.csdn.net/guorui_java/article/details/107379648\">Spring Boot 常用注解（绝对经典）</a></p>\n</blockquote>\n<hr>\n<h4 id=\"日志\">日志</h4>\n<blockquote>\n<p><a href=\"https://blog.csdn.net/u013068377/article/details/107239878\">Java 最详细常用日志框架介绍</a></p>\n</blockquote>\n<hr>\n<h3 id=\"工具类\">工具类</h3>\n<h4 id=\"I-O\">I/O</h4>\n<blockquote>\n<p>序列化 /ObjectOutputStream <a href=\"https://blog.csdn.net/cc1969281777/article/details/87068106\">对象操作流 ObjectOutputStream</a></p>\n</blockquote>\n<hr>\n<h4 id=\"OPTIONAL\">OPTIONAL</h4>\n<blockquote>\n<p><a href=\"https://www.cnblogs.com/zhangboyu/p/7580262.html\">理解、学习与使用 JAVA 中的 OPTIONAL</a></p>\n</blockquote>\n<h4 id=\"URL\">URL</h4>\n<blockquote>\n<p><a href=\"https://www.cnblogs.com/kissdodog/archive/2013/04/22/3034898.html\">System.Uri 类 - 获取 Url 的各种属性，文件名，参数，域名，端口等等</a></p>\n</blockquote>\n<h4 id=\"Stream\">Stream</h4>\n<blockquote>\n<p><a href=\"https://blog.csdn.net/happyheng/article/details/52832313\">Java8 Stream 详解</a></p>\n</blockquote>\n<h4 id=\"单元测试 -Junit\">单元测试 Junit</h4>\n<blockquote>\n<p><a href=\"https://mp.weixin.qq.com/s?__biz=MzIxNzQwNjM3NA==&amp;mid=2247490821&amp;idx=1&amp;sn=855b8ede1287dd95787a010c3245c8e7&amp;chksm=97fb13cca08c9ada0af423bc4e94ba359d810c32c23ab2a546abaaf30e152c92b826efc1c01f&amp;xtrack=1&amp;scene=90&amp;subscene=93&amp;sessionid=1609292024&amp;clicktime=1609292488&amp;enterid=1609292488&amp;ascene=56&amp;devicetype=android-29&amp;version=27001637&amp;nettype=WIFI&amp;abtest_cookie=AAACAA%3D%3D&amp;lang=zh_CN&amp;exportkey=Af%2BuVL395LWe0DRJ%2Fc8R%2FbA%3D&amp;pass_ticket=6zFqmo%2F%2Fh%2B276SfQuaklQyBIbfcB0rcAk2nXRgO9SV%2FEeTr8pGbFXbfRhR%2FDXMx%2F&amp;wx_header=1\">JUnit：别再用 main 方法测试了，好吗？</a></p>\n</blockquote>\n<p><a><img src= \"https://cdn.jsdelivr.net/gh/Weidows/Images/img/loading.webp\" data-lazy-src=\"https://cdn.jsdelivr.net/gh/Weidows/Images/img/divider.png\" alt=\"分割线\"></a></p>\n<h2 id=\"前端 -2\">前端</h2>\n<h3 id=\"HTML-CSS\">HTML/CSS</h3>\n<ul>\n<li>一般这俩是合在一起学的, 相关性较强.</li>\n<li>都是 <code> 前端基础</code>, 但是后端也必须要会.</li>\n</ul>\n<hr>\n<h4 id=\"入门 -2\">入门</h4>\n<blockquote>\n<p><a href=\"https://www.bilibili.com/video/BV14J4114768\">黑马程序员 pink 老师前端入门视频教程 HTML5+CSS3+ 移动端布局 -flex 布局 rem 布局响应式布局摹客蓝湖使用 - 简单有趣好玩</a></p>\n</blockquote>\n<ul>\n<li>全网最知名的 HTML/css 基础讲师 - 黑马程序员 pink, 应该没有之一了(至少到 2020 为止)\n<ul>\n<li>虽然他说话有些风骚</li>\n</ul>\n</li>\n<li>视频贼多, 我没看完, 把基础趟完跑路.</li>\n</ul>\n<hr>\n<h4 id=\"进阶 -2\">进阶</h4>\n<blockquote>\n<p><a href=\"https://www.bilibili.com/video/BV1YJ411a7dy\">【狂神说 Java】CSS3 最新教程快速入门通俗易懂</a></p>\n</blockquote>\n<ul>\n<li>一个字, 很不错!</li>\n</ul>\n<h4 id=\"Markdown-2\">Markdown</h4>\n<ul>\n<li>\n<p>这个没有什么特效课程, 需要循序渐进的使用 markdown 记笔记, 把一些关键词用熟悉, 渐渐地文章就变得好起来了</p>\n</li>\n<li>\n<p>markdown 这种 <code> 归档式 </code>,<code> 目录式 </code> 以及 <code> 层级递进式 </code> 的笔记记录方式, 能很好地 <code> 锻炼表达思维</code>, 而且对学习效果有显著提升.</p>\n</li>\n</ul>\n<p><a><img src= \"https://cdn.jsdelivr.net/gh/Weidows/Images/img/loading.webp\" data-lazy-src=\"https://cdn.jsdelivr.net/gh/Weidows/Images/img/divider.png\" alt=\"分割线\"></a></p>\n<h3 id=\"JavaScript\">JavaScript</h3>\n<h4 id=\"进阶 -3\">进阶</h4>\n<blockquote>\n<p><a href=\"https://www.bilibili.com/video/BV1JJ41177di\">【狂神说 Java】JavaScript 最新教程通俗易懂</a></p>\n</blockquote>\n<ul>\n<li>\n<p>因为有 Java 基础, 入门阶段直接过去了.</p>\n<ul>\n<li>\n<p>狂神老师出的都很…上头!</p>\n</li>\n<li>\n<p>就是那个味!</p>\n</li>\n</ul>\n</li>\n</ul>\n<hr>\n<h4 id=\"异步\">异步</h4>\n<blockquote>\n<p><a href=\"https://segmentfault.com/a/1190000007535316\">理解 JavaScript 的 async/await</a></p>\n</blockquote>\n<hr>\n<h4 id=\"Console\">Console</h4>\n<blockquote>\n<p><a href=\"http://cn.voidcc.com/question/p-nyquxitt-dn.html\">如何在控制台中隐藏日志消息的来源？</a></p>\n</blockquote>\n<blockquote>\n<p><a href=\"https://www.cnblogs.com/suwanbin/p/13383064.html\">js 控制台 console 骚操作 - 打印图片 - 自定义样式 - 字符画</a></p>\n</blockquote>\n<ul>\n<li>可以在网站中做一些有意思的事, 比如在我的博客这里, 按 <code>F12</code> 可以看到.</li>\n</ul>\n<hr>\n<h4 id=\"闭包\">闭包</h4>\n<blockquote>\n<p><a href=\"https://www.jb51.net/article/166905.htm\">JS 自执行函数原理及用法</a></p>\n</blockquote>\n<hr>\n<h4 id=\"Ajax\">Ajax</h4>\n<blockquote>\n<p><a href=\"https://www.bilibili.com/video/BV1Kt411u7BV\">【狂神说 Java】一小时掌握 Ajax</a></p>\n</blockquote>\n<hr>\n<h3 id=\"大前端\">大前端</h3>\n<h4 id=\"Vue-js\">Vue.js</h4>\n<ul>\n<li>\n<p>啊这, 这文章快成推销了</p>\n<p>有一段时间没跟着视频学习了, 光看文章的话, 学起来还挺快</p>\n<blockquote>\n<p><a href=\"https://blog.csdn.net/DDDDeng_/article/details/107475920\">狂神说 Vue 笔记</a></p>\n</blockquote>\n</li>\n</ul>\n<hr>\n<h4 id=\"跨域\">跨域</h4>\n<blockquote>\n<p><a href=\"./../../Web/JavaScript/CORS\">😡 一次解决 CORS 经验记录.</a></p>\n</blockquote>\n<hr>\n<h4 id=\"工具类 -2\">工具类</h4>\n<ul>\n<li>\n<p>干活时搞了一下午.map, 被这个问答糊脸了</p>\n<blockquote>\n<p><a href=\"https://www.it1352.com/1014899.html\">为什么 javascript map 函数返回 undefined？(Why does javascript map function return undefined?)</a></p>\n</blockquote>\n</li>\n</ul>\n<h4 id=\"其他\">其他</h4>\n<p><a href=\"https://mp.weixin.qq.com/s/qNJPkSkMTWNYjjKMp4rwmA\">如何做到修改 node_module 中的包，却不受重新安装的影响</a></p>\n<p><a><img src= \"https://cdn.jsdelivr.net/gh/Weidows/Images/img/loading.webp\" data-lazy-src=\"https://cdn.jsdelivr.net/gh/Weidows/Images/img/divider.png\" alt=\"分割线\"></a></p>\n<h2 id=\"辅助语言\">辅助语言</h2>\n<h3 id=\"C-C\">C/C++</h3>\n<ul>\n<li>\n<p>个人比较喜欢把 C 和 C++ 放在一起, 虽然 C++ 并没学过(不过倒是能看懂).</p>\n</li>\n<li>\n<p>全程学的 <code> 翁凯 </code> 老师的, 讲的很好.</p>\n</li>\n</ul>\n<h4 id=\"入门课程\">入门课程</h4>\n<blockquote>\n<p><a href=\"https://www.icourse163.org/course/0809ZJU007A-199001?outvandor=zw_mooc_pclszykctj_\">程序设计入门——C 语言</a></p>\n</blockquote>\n<h4 id=\"进阶课程\">进阶课程</h4>\n<blockquote>\n<p><a href=\"https://www.icourse163.org/course/ZJU-200001\">C 语言程序设计进阶</a></p>\n</blockquote>\n<h4 id=\"链表\">链表</h4>\n<blockquote>\n<p><a href=\"https://www.bilibili.com/video/BV1Rb411F738\">1 个小时学会单链表，C 语言数据结构专题</a></p>\n</blockquote>\n<hr>\n<h3 id=\"Python\">Python</h3>\n<ul>\n<li>\n<p>菜鸟教程:</p>\n<blockquote>\n<p><a href=\"https://www.runoob.com/python3/python3-tutorial.html\">Python 3 教程</a></p>\n</blockquote>\n</li>\n</ul>\n<h4 id=\"工具\">工具</h4>\n<blockquote>\n<p><a href=\"https://www.cnblogs.com/wanglvtao/p/11140025.html\">Python 配置管理的几种方式</a> <br>\n<a href=\"https://blog.csdn.net/qq_42967398/article/details/88078788\">Python 类型强制转换和字符串的操作</a></p>\n</blockquote>\n<p><a><img src= \"https://cdn.jsdelivr.net/gh/Weidows/Images/img/loading.webp\" data-lazy-src=\"https://cdn.jsdelivr.net/gh/Weidows/Images/img/divider.png\" alt=\"分割线\"></a></p>\n<h2 id=\"开发工具\">开发工具</h2>\n<h3 id=\"Git\">Git</h3>\n<ul>\n<li>\n<p>这应该是所有程序员必会的技能了, 没有保留的余地.</p>\n</li>\n<li>\n<p>学 Git 嘛, 说来也不用学, 装上 git 之后结合 <code>github</code> 摸索摸索就会了.</p>\n</li>\n<li>\n<p>前前后后用过的 git 可视化程序有 <code>SourceTree</code>,<code>gitkraken</code>,<code>github</code>,<code>vscode</code> 等等…</p>\n</li>\n<li>\n<p>要是说建议路线嘛, 推荐先入手<code>vscode</code>, 特容易上手, 然后是<code>SourceTree</code>, 这个可以对很多深入功能有较强的理解, 反正我最后用的是<code>VScode + gitgraph 插件</code>, 足够了.</p>\n</li>\n</ul>\n<hr>\n<h4 id=\"Git-push\">Git push</h4>\n<blockquote>\n<p><a href=\"https://www.cnblogs.com/qianqiannian/p/6008140.html\">Git push 常见用法</a></p>\n</blockquote>\n<hr>\n<h4 id=\"多远程\">多远程</h4>\n<blockquote>\n<p><a href=\"https://segmentfault.com/a/1190000011294144\">一个项目 push 到多个远程 Git 仓库</a></p>\n</blockquote>\n<p><a><img src= \"https://cdn.jsdelivr.net/gh/Weidows/Images/img/loading.webp\" data-lazy-src=\"https://cdn.jsdelivr.net/gh/Weidows/Images/img/divider.png\" alt=\"分割线\"></a></p>\n<h3 id=\"VScode-2\">VScode</h3>\n<h4 id=\"主题适配\">主题适配</h4>\n<blockquote>\n<p><a href=\"https://blog.csdn.net/weixin_45599654/article/details/109306462\">VScode 自定义主题 界面 UI 配色 语法配色</a></p>\n</blockquote>\n<hr>\n<h4 id=\"插件 - 包 - 开发 - 发布\">插件 (包) 开发 / 发布</h4>\n<blockquote>\n<p><a href=\"https://segmentfault.com/a/1190000020435312\">VScode 插件开发（五）插件包</a></p>\n</blockquote>\n<hr>\n<h4 id=\"Emmet\">Emmet</h4>\n<blockquote>\n<p><a href=\"https://blog.csdn.net/qq_33744228/article/details/80910377\">【Emmet】HTML 速写之 Emmet 语法规则</a></p>\n</blockquote>\n<hr>\n<h3 id=\"Docker\">Docker</h3>\n<blockquote>\n<p><a href=\"https://www.bilibili.com/video/BV1vD4y1X7ce\">初探 Docker</a></p>\n</blockquote>\n<hr>\n<h3 id=\"正则表达式\">正则表达式</h3>\n<blockquote>\n<p><a href=\"https://github.com/ziishaned/learn-regex/blob/master/translations/README-cn.md\">ziishaned/learn-regex</a></p>\n</blockquote>\n<ul>\n<li>标星超高的项目, 必须一刷!</li>\n</ul>\n<p><a><img src= \"https://cdn.jsdelivr.net/gh/Weidows/Images/img/loading.webp\" data-lazy-src=\"https://cdn.jsdelivr.net/gh/Weidows/Images/img/divider.png\" alt=\"分割线\"></a></p>\n<h2 id=\"泛域\">泛域</h2>\n<h3 id=\"2038- 问题\">2038 问题</h3>\n<blockquote>\n<p><a href=\"https://baike.baidu.com/item/2038%E5%B9%B4%E9%97%AE%E9%A2%98/10578442?fr=aladdin\">2038 年问题</a></p>\n<ul>\n<li>问题不大不小,Windows 平台与 linux 平台都有相应的推迟解决方案了.</li>\n</ul>\n</blockquote>\n<hr>\n<h3 id=\"自信\">自信</h3>\n<blockquote>\n<p><a href=\"https://blog.csdn.net/m0_46163918/article/details/114883501?utm_source=app&amp;app_version=4.5.4\">上班 4 年，现在却只会调工具包，AI 程序员崩溃了</a></p>\n</blockquote>\n<ul>\n<li>\n<p>随着年龄的增大, 越发发现自信的重要性.</p>\n</li>\n<li>\n<p>初中时就被体育老师洗脑, 直到现在仍然感觉带有自信头衔的人有独特的美丽.</p>\n</li>\n<li>\n<p>当然, 自信不是自负, 是 <code> 合理的外向 + 阳光 + 乐观 </code> 的态度, 在社交, 职场和情感方面都有一定作用.</p>\n</li>\n<li>\n<p>我发现我好想也有点文中提到的“冒名顶替综合征”, 文中也有我认为很好的解决办法:</p>\n<ol>\n<li>多多交流和分享</li>\n<li>记录做过的事情</li>\n<li>保持学习者心态</li>\n</ol>\n</li>\n</ul>\n<hr>\n<h3 id=\"编码习惯\">编码习惯</h3>\n<blockquote>\n<p><a href=\"https://mp.weixin.qq.com/s?__biz=MzA5NDIzNzY1OQ==&amp;mid=2735619936&amp;idx=1&amp;sn=56562e359badd5afb27529ebc41d77b9&amp;chksm=b6ab39d481dcb0c21f5696373b0882fdfc0a06cbce7e4cf45529847012a1990b0758d45e6244&amp;mpshare=1&amp;scene=23&amp;srcid=0505Bype3cbVTtcSBVgUS3Ed&amp;sharer_sharetime=1620190642862&amp;sharer_shareid=ff6bb8cfd138294e80df076b8b76232d#rd\">优秀程序员都在注意的 10 个点</a></p>\n</blockquote>\n<hr>\n<h3 id=\"文档编写\">文档编写</h3>\n<ul>\n<li>\n<p>emmm,Ummm…这是个如何优雅拉屎的艺术</p>\n<blockquote>\n<p><a href=\"https://www.jianshu.com/p/a7984927cfb9\">最全！软件开发类项目关键文档内容要求</a> <br>\n<a href=\"https://www.jianshu.com/p/a52fe78962f0\">软件需求，概要设计，详细设计（文档）怎么做，做什么？</a></p>\n</blockquote>\n</li>\n<li>\n<p>一个挺像样的项目文档:</p>\n<blockquote>\n<p><a href=\"https://wenku.baidu.com/view/1e0708f41611cc7931b765ce05087632311274cf.html\">软件项目开发文档</a></p>\n</blockquote>\n</li>\n</ul>\n<hr>\n<h3 id=\"代理\">代理</h3>\n<blockquote>\n<p><a href=\"https://congcong0806.github.io/2018/04/20/SS/\">SS/SSR/V2Ray/Clash 简介和客户端软件下载</a></p>\n</blockquote>\n<h3 id=\"图灵测试\">图灵测试</h3>\n<blockquote>\n<ul>\n<li>问题来自于 <a href=\"https://mathpix.com/\">mathpix</a> 这个官网首页, 玩梗 😂<br>\n<img src= \"https://cdn.jsdelivr.net/gh/Weidows/Images/img/loading.webp\" data-lazy-src=\"https://cdn.jsdelivr.net/gh/Weidows/Images/post/Zz1HM8Krk69idf4.png\" alt=\"QQ 截图 20210626151150\" /><br>\n<a href=\"https://zh.wikipedia.org/wiki/%E5%9B%BE%E7%81%B5%E6%B5%8B%E8%AF%95\">维基百科: 图灵测试</a></li>\n</ul>\n</blockquote>\n<hr>\n<h3 id=\"IaaS，PaaS，SaaS\">IaaS，PaaS，SaaS</h3>\n<blockquote>\n<p><a href=\"https://www.ruanyifeng.com/blog/2017/07/iaas-paas-saas.html\">IaaS，PaaS，SaaS 的区别</a></p>\n</blockquote>\n<p><a><img src= \"https://cdn.jsdelivr.net/gh/Weidows/Images/img/loading.webp\" data-lazy-src=\"https://cdn.jsdelivr.net/gh/Weidows/Images/img/divider.png\" alt=\"分割线\"></a></p>\n<h2 id=\"设计\">设计</h2>\n<ul>\n<li>\n<p>跳到新文章吧, 写在这太长.</p>\n<blockquote>\n<p><a href=\"../../design/UI-design\">🙌UI 平面设计.</a></p>\n</blockquote>\n</li>\n</ul>\n<p><a><img src= \"https://cdn.jsdelivr.net/gh/Weidows/Images/img/loading.webp\" data-lazy-src=\"https://cdn.jsdelivr.net/gh/Weidows/Images/img/divider.png\" alt=\"分割线\"></a></p>\n<h2 id=\"理论课程\">理论课程</h2>\n<h3 id=\"数据结构\">数据结构</h3>\n<blockquote>\n<p><a href=\"https://www.cnblogs.com/zmc940317/articles/10925497.html\">二叉树的前, 中, 后序遍历详解</a></p>\n</blockquote>\n<hr>\n<h3 id=\"操作系统\">操作系统</h3>\n<blockquote>\n<p><a href=\"https://blog.csdn.net/qq_33414271/article/details/80245715\">一句话 + 一张图说清楚——银行家算法</a> <br>\n<a href=\"https://blog.csdn.net/a745233700/article/details/86011504\">操作系统：经典进程同步问题 之 生产者 - 消费者问题、读者 - 写者问题、哲学家进餐问题</a> <br>\n<a href=\"https://blog.csdn.net/lala_wang/article/details/81116781?utm_medium=distribute.pc_relevant.none-task-blog-baidujs_title-0&amp;spm=1001.2101.3001.4242\">调度算法的介绍及优缺点</a></p>\n</blockquote>\n<h4 id=\"进程 - 线程 -CPU- 核心 - 并行 - 并发\">进程, 线程,CPU 核心, 并行, 并发</h4>\n<blockquote>\n<p>我给总结了一下: <a href=\"../../system/process-thread\">🤷‍♂️ 进程, 线程,CPU 核心, 并行, 并发大杂碎!</a></p>\n</blockquote>\n<hr>\n<h3 id=\"编译原理\">编译原理</h3>\n<blockquote>\n<p><a href=\"https://blog.csdn.net/qq_39384184/article/details/86037568\">编译原理：总结</a> <br>\n结合其他视频或者课程阅读, 效果更好些.</p>\n</blockquote>\n<hr>\n<h3 id=\"硬件\">硬件</h3>\n<blockquote>\n<p><a href=\"https://www.bilibili.com/video/BV1sE411L7j5\">【一天掌握 51 单片机基础】<em>单片机原理及应用 </em> 东北大学（高宏亮 主讲）</a> <br>\n比较通俗易懂, 课程 / 课件质量相当高.</p>\n</blockquote>\n<hr>\n<h3 id=\"数据库\">数据库</h3>\n<h4 id=\"MySQL\">MySQL</h4>\n<ul>\n<li>\n<p>要点清晰, 能很快速的顺下来需要掌握的东西.</p>\n<blockquote>\n<p><a href=\"https://www.bilibili.com/video/BV1NJ411J79W\">【狂神说 Java】MySQL 最新教程通俗易懂</a> <br>\n<a href=\"https://blog.csdn.net/weixin_45483328/article/details/113759286?utm_medium=distribute.pc_relevant.none-task-blog-BlogCommendFromMachineLearnPai2-2.control&amp;dist_request_id=&amp;depth_1-utm_source=distribute.pc_relevant.none-task-blog-BlogCommendFromMachineLearnPai2-2.control\">狂神说数据库笔记</a></p>\n</blockquote>\n</li>\n</ul>\n<hr>\n<h4 id=\"MongoDB\">MongoDB</h4>\n<ul>\n<li>\n<p>有 MySQL 基础能很快上手</p>\n<blockquote>\n<p><a href=\"https://github.com/krislinzhao/StudyNotes/tree/master/MongoDB\">krislinzhao/StudyNotes</a></p>\n</blockquote>\n</li>\n</ul>\n<hr>\n<h4 id=\"通用\">通用</h4>\n<blockquote>\n<ol>\n<li>质量相当高的文章: <a href=\"https://blog.csdn.net/wxwzy738/article/details/17590305\">MySQL 单列索引和组合索引的区别介绍</a></li>\n<li><a href=\"https://mp.weixin.qq.com/s/3ZdACGiA0SutmbDxMeF-UA\">我们为什么要分库分表？</a> <br>\n这篇封神了, 把我最近在数据库业务设计方面的疑问解决了.</li>\n</ol>\n</blockquote>\n<hr>\n<h3 id=\"计算机网络\">计算机网络</h3>\n<blockquote>\n<p><a href=\"https://blog.csdn.net/hexf9632/article/details/93469788\">IP 地址，子网掩码、默认网关，DNS 服务器之间的联系与区别</a></p>\n</blockquote>\n<hr>\n<h3 id=\"算法 - 数学\">算法 - 数学</h3>\n<h4 id=\"傅里叶变换\">傅里叶变换</h4>\n<blockquote>\n<p><a href=\"../../experience/basic/%E9%80%9A%E4%BF%A1%E6%8A%80%E6%9C%AF#%E5%82%85%E9%87%8C%E5%8F%B6%E5%8F%98%E6%8D%A2\">👽 通信技术 - 开坑自埋</a></p>\n</blockquote>\n<h4 id=\"P-NP- 问题\">P/NP 问题</h4>\n<blockquote>\n<ol>\n<li><a href=\"https://baike.baidu.com/item/P%E5%AF%B9NP%E9%97%AE%E9%A2%98\">P 对 NP 问题</a></li>\n<li><a href=\"https://www.omegaxyz.com/2019/04/22/np/?hilite=%27filled%27,%27o.e.m%27\">算法复杂度与 NP 问题</a></li>\n<li><a href=\"http://www.cainiaoxueyuan.com/suanfa/4517.html\">贪婪算法案例、np 完全问题及 java 代码实现</a> <br>\n非常经典和值得探索的问题 (经验接收自<code>@河北工业大学</code>)</li>\n</ol>\n</blockquote>\n<hr>\n<h4 id=\"Hash- 算法\">Hash- 算法</h4>\n<ul>\n<li>\n<p>用来校验文本 / 文件, 主流有三类, 不同算法产生的 hash code 不同</p>\n<p>MD5</p>\n<p>CRC-32, CRC-64</p>\n<p>SHA-1, SHA-256, SHA-384, SHA-512</p>\n</li>\n</ul>\n<blockquote>\n<p>校验方法: <a href=\"https://blog.csdn.net/weixin_30799995/article/details/94896898\">文件完整性校验</a></p>\n</blockquote>\n<hr>\n<h4 id=\"排序算法\">排序算法</h4>\n<blockquote>\n<ul>\n<li><a href=\"https://mp.weixin.qq.com/s?__biz=Mzg3MzU2Njk3MA==&amp;mid=2247492793&amp;idx=1&amp;sn=79ab61671459c3a2d627d5a3e1eb7ec0&amp;chksm=cedca32cf9ab2a3aabf3b02d26c991ca4f56a49078a28ad97433c6645d003b559de4e98e706d&amp;mpshare=1&amp;scene=23&amp;srcid=1019M2F6aYi9B8WEFHtfu4sr&amp;sharer_sharetime=1634632120052&amp;sharer_shareid=ff6bb8cfd138294e80df076b8b76232d#rd\">上厕所的功夫，学会了快速排序算法</a><br>\n在某区间中取最左 / 最右为基准, 并给定左右两边移动指针;<br>\n左边有坑取有指针的值比较, 比基准大的话不动, 小的话移动到左边的坑; 右边有坑时相反.</li>\n<li><a href=\"https://www.cnblogs.com/chengxiao/p/6194356.html\">图解排序算法 (四) 之归并排序</a></li>\n</ul>\n</blockquote>\n<hr>\n<h4 id=\"其他零散的\">其他零散的</h4>\n<blockquote>\n<ol>\n<li><a href=\"https://blog.csdn.net/qq_30268545/article/details/80600064\">棋盘覆盖问题 - 分治法</a></li>\n<li><a href=\"https://blog.csdn.net/qq_19782019/article/details/94356886\">动态规划之——矩阵连乘（全网最详细博文，看这一篇就够了！）</a></li>\n</ol>\n</blockquote>\n<hr>\n<h3 id=\"论文\">论文</h3>\n<blockquote>\n<ol>\n<li><a href=\"https://cloud.tencent.com/developer/news/231960\">如何将 CNKI 论文信息转换成你想要的参考文献格式</a> 关键时候挺好用的功能</li>\n<li><a href=\"https://www.zhihu.com/question/381137645\">论文引用怎么标注？</a></li>\n</ol>\n</blockquote>\n<p><a><img src= \"https://cdn.jsdelivr.net/gh/Weidows/Images/img/loading.webp\" data-lazy-src=\"https://cdn.jsdelivr.net/gh/Weidows/Images/img/divider.png\" alt=\"分割线\"></a></p>\n<h2 id=\"面试\">面试</h2>\n<blockquote>\n<ol>\n<li><a href=\"https://blog.csdn.net/weixin_38607253/article/details/114154414\">MetaAPP 部分笔试题</a></li>\n<li><a href=\"https://www.cnblogs.com/guoxiaoyan/p/8664150.html\">什么是“堆”,“栈”,“堆栈”,“队列”, 它们的区别</a></li>\n<li><a href=\"https://www.cnblogs.com/timecloud/p/6555868.html\">到底产生几个 String 对象</a></li>\n<li><a href=\"https://www.cnblogs.com/dolphin0520/p/3592500.html\">浅谈 Java 中的 equals 和 ==</a></li>\n<li><a href=\"https://mp.weixin.qq.com/s/SytfnrsYqequ2M7CnSY-IA\">字节终面：两个文件的公共 url 怎么找？</a> / <a href=\"https://mp.weixin.qq.com/s/TdJWFxrDAadK9UXar4WiRA\">小米面试：孔融找梨</a> <br>\n通过 hash 降低时间复杂度, 以及通过 hash 分治降低空间复杂度</li>\n</ol>\n</blockquote>\n<script type=\"text&#x2F;javascript\" src=\"https://unpkg.com/kity@2.0.4/dist/kity.min.js\"></script><script type=\"text&#x2F;javascript\" src=\"https://unpkg.com/kityminder-core@1.4.50/dist/kityminder.core.min.js\"></script><script defer=\"true\" type=\"text&#x2F;javascript\" src=\"https://unpkg.com/hexo-simple-mindmap@0.8.0/dist/mindmap.min.js\"></script><link rel=\"stylesheet\" type=\"text&#x2F;css\" href=\"https://unpkg.com/hexo-simple-mindmap@0.8.0/dist/mindmap.min.css\">",
            "tags": [
                "备忘录",
                "成长路线",
                "deprecated"
            ]
        },
        {
            "id": "https://weidows.github.io/post/others/Lord_road/",
            "url": "https://weidows.github.io/post/others/Lord_road/",
            "title": "成长路线 (倒叙)",
            "date_published": "2020-11-17T03:06:25.000Z",
            "content_html": "<!--\n * @Author: Weidows\n * @Date: 2020-11-17 11:06:25\n * @LastEditors: Weidows\n * @LastEditTime: 2021-07-04 11:07:21\n * @FilePath: \\Weidowsd:\\Game\\Github\\Blog-private\\source\\_posts\\others\\Lord_road.md\n * @Description: 成长路线\n-->\n<ul>\n<li><a href=\"#2021-07-04\">2021-07-04</a></li>\n<li><a href=\"#2021-03-14\">2021-03-14</a>\n<ul>\n<li><a href=\"#%E6%B5%81%E9%87%8F%E5%BC%95%E5%85%A5\"> 流量引入 </a></li>\n<li><a href=\"#%E7%94%9F%E5%AD%98%E5%91%A8%E6%9C%9F\"> 生存周期 </a></li>\n<li><a href=\"#%E5%91%88%E7%8E%B0%E9%9A%BE%E5%BA%A6\"> 呈现难度 </a></li>\n<li><a href=\"#%E4%BA%8E%E6%98%AF\"> 于是 </a></li>\n</ul>\n</li>\n<li><a href=\"#2020-11-17\">2020-11-17</a></li>\n</ul>\n<h2 id=\"2021-07-04\">2021-07-04</h2>\n<p> 我犯了一个很大的错误 </p>\n<ul>\n<li>\n<p> 我向来总是喜欢 &quot; 堡垒化学习 &quot;, 什么意思呢?</p>\n<p> 学到某一方面时不再走出这个小领域, 并且企图把这块领域盖起很扎实的堡垒 </p>\n<p> 看似没问题, 打基础确实重要啊?</p>\n</li>\n</ul>\n<p> 但这导致我眼界受限, 看东西很死, 不到某个阶段就感觉学不会某个东西, 而且学东西很喜欢时效化 (那种按部就班的学习)</p>\n<p> 走到现在我发现, 大多数技术栈是从了解 -&gt; 熟悉 -&gt; 精通这么发展的 </p>\n<ul>\n<li>\n<p> 我需要走理念性通吃道路:</p>\n<p> 最近在学 Spring, 看到很多教程按照 Spring-&gt;SpringMVC-&gt;SpringBoot 这么来教的, 并没有错误, 我也感觉很正确 </p>\n<p> 但现在我认为最适合我的道路是并行吃, 把 IoC/AOP 理念弄懂 -&gt; 熟悉操作 -&gt; 研究源码 这么个道路更合适我 </p>\n</li>\n</ul>\n<blockquote>\n<p> 知识深度的价值在学习某个子进程中并没有知识广度高 </p>\n</blockquote>\n<p> 通俗点讲就是我在某一个小区域花死劲了.</p>\n<p><a><img src= \"https://cdn.jsdelivr.net/gh/Weidows/Images/img/loading.webp\" data-lazy-src=\"https://cdn.jsdelivr.net/gh/Weidows/Images/img/divider.png\" alt=\"分割线\"></a></p>\n<h2 id=\"2021-03-14\">2021-03-14</h2>\n<p> 再寻信息流向.log 理理头绪 </p>\n<p> 不得不说我这专业吃流量和用户量，个人并不想通过恶意营销和广告形式引流。<br>\n博客开了一段日子了，结合实际来看发现很多问题。此处与主流的视频媒体和公众号横向对比下。</p>\n<h3 id=\"流量引入\"> 流量引入 </h3>\n<p> 不大不小的问题，通过 SEO 可以解决一部分弊病，品牌 IP 塑造前期格外艰难，即使有优秀的作品，在成相当的体量之前，用户量提升很小。<br>\nSEO 方面，谷歌＞必应＞百度，准确度和收录速度差好几条街 </p>\n<h3 id=\"生存周期\"> 生存周期 </h3>\n<p> 个人发现博客和网站的生存周期远远大于视频媒体。比如写个博客发在 CSDN 上，一般来说价值有效期在三年范围内。而同样的内容在视频媒体呈现上，价值生存周期比较难突破三个月。而最后的公众号，更是惨，点赞－收藏－之后没了，SEO 收录不到，推荐系统更是辣鸡。</p>\n<h3 id=\"呈现难度\"> 呈现难度 </h3>\n<p> 视频＞公众号＞博客 <br>\n也有一种现象，有的人视频做的贼好，但是内容吸引度低，上不高大上，下不接地气，精力收成比低。<br>\n公众号很容易上手，但是流量吸引极其靠人脉 IP，只能从其他平台已有 IP 进行横向迁移，其他途径，男上加男。<br>\n博客的话，更像是插排，它的功能用处和价值体现靠开发者本身，单说内容呈现难度来说很低，精力收成比较高，但是很大程度上不为大多数人所接受。</p>\n<h3 id=\"于是\"> 于是 </h3>\n<p> 写到这里，就是为了记录一下，整理下思路，并寻找下一代内容呈现方式。<br>\n这或许是二十一世纪二十年代的风口，不知会被谁打破当局。</p>\n<p><a><img src= \"https://cdn.jsdelivr.net/gh/Weidows/Images/img/loading.webp\" data-lazy-src=\"https://cdn.jsdelivr.net/gh/Weidows/Images/img/divider.png\" alt=\"分割线\"></a></p>\n<h2 id=\"2020-11-17\">2020-11-17</h2>\n<ul>\n<li>\n<p>JAVA 初级工程师 9k-15k 一般是 1-3 年的经验 <br>\n要求：掌握 <br>\nJAVA 基础，spring springmvc mybatis servlet restful，webservice，h5 css3 JavaScript jquery angular vue。<br>\n常用的服务器技术：tomcat，apache nginx。<br>\ngit maven redis dubbo zookeeper<br>\n同时还有 多线程，设计模式，JAVA io nio<br>\n网络方面：tcp，udp，netty</p>\n</li>\n<li>\n<p>JAVA 中级工程师 15k-25k 一般是 3-5 年的经验 <br>\n要求：精通 <br>\nspringcloud dubbo。<br>\n还得熟悉一些中间件技术：分布式技术，rpc 技术，缓存，消息系统。<br>\n懂互联网业务，要求有大规模高并发访问 web 应用的经验。<br>\n熟悉一些虚拟化技术：docker，vmware，openstack。<br>\n深入理解数据结构和算法。<br>\n精通设计模式（至少常用的七八种设计模式必须达到精通的水平），就是能用到设计模式到项目中，让项目的代码更规范。</p>\n</li>\n<li>\n<p>JAVA 高级工程师 25k-35k 一般是 3-5 年 <br>\n得会开发，设计还得有领导能力，必须能带领一个团队，分析产品技术设计，负责新功能的技术开发，参与平台的需求分析，业务规划，帮助团队成员解决技术问题。决定技术方向和业务选型。<br>\n有些公司还会要求你了解大数据的一些技术；hadoop impala spark flink 主流的大数据框架 <br>\n精通 jvm 内存管理，要会 jvm 调优 <br>\n熟悉分布式常用技术，</p>\n</li>\n<li>\n<p>JAVA 架构师（研发经理）40k-60k 一般是 5-10 年 <br>\n参与微服务架构的设计和落地。要发觉和解决复杂问题，关键技术的公关和改进现有的架构。<br>\n就是着重于优化和架构设计的工作。要精通多线程，要有高并发，大数据处理的经验。可能会要求主导过大型高可用，高并发，分布式，自动化的项目经验。熟悉自动化部署技术比如 k8s</p>\n</li>\n</ul>\n<script type=\"text&#x2F;javascript\" src=\"https://unpkg.com/kity@2.0.4/dist/kity.min.js\"></script><script type=\"text&#x2F;javascript\" src=\"https://unpkg.com/kityminder-core@1.4.50/dist/kityminder.core.min.js\"></script><script defer=\"true\" type=\"text&#x2F;javascript\" src=\"https://unpkg.com/hexo-simple-mindmap@0.8.0/dist/mindmap.min.js\"></script><link rel=\"stylesheet\" type=\"text&#x2F;css\" href=\"https://unpkg.com/hexo-simple-mindmap@0.8.0/dist/mindmap.min.css\">",
            "tags": [
                "备忘录",
                "成长路线"
            ]
        }
    ]
}